wsfx/__init__.py
wsfx/ws.py
wsfx_genwch-0.0.2.dist-info/LICENSE
wsfx_genwch-0.0.2.dist-info/METADATA
wsfx_genwch-0.0.2.dist-info/WHEEL
wsfx_genwch-0.0.2.dist-info/top_level.txt
wsfx_genwch-0.0.2.dist-info/RECORD
